Metadata-Version: 1.0
Name: pystat-distributions
Version: 1.0
Summary: Gaussian and Binomial distributions
Home-page: UNKNOWN
Author: Tara Haddadin
Author-email: tara_haddadin@yahoo.com
License: UNKNOWN
Platform: UNKNOWN
